gist_cli-0.1.2.dist-info/licenses/LICENSE.txt
gst/__init__.py
gst/main.py
gst/commands/__init__.py
gst/commands/auth.py
gst/commands/clone.py
gst/commands/create.py
gst/services/__init__.py
gst/services/http.py
gst/services/token_setter.py
gist_cli-0.1.2.dist-info/METADATA
gist_cli-0.1.2.dist-info/WHEEL
gist_cli-0.1.2.dist-info/entry_points.txt
gist_cli-0.1.2.dist-info/top_level.txt
gist_cli-0.1.2.dist-info/RECORD
