Metadata-Version: 2.4
Name: gist-cli
Version: 0.1.2
Summary: GitHub Gist cli without github, only gist.
Author-email: Adrian Makridenko <adrianmakridenko@duck.com>
License: Apache-2.0 license
Project-URL: Homepage, https://gst.makridenko.ru
Project-URL: Repository, https://github.com/lyaguxafrog/gst
Project-URL: Issues, https://github.com/lyaguxafrog/gst/issues
Keywords: cli,gist,github,httpx,keyring,click
Requires-Python: >=3.13
License-File: LICENSE.txt
Requires-Dist: click>=8.3.0
Requires-Dist: httpx>=0.28.1
Requires-Dist: keyring>=25.6.0
Dynamic: license-file
